teflo_notify_service_plugin/__init__.py
teflo_notify_service_plugin/notify_service_plugin.py
teflo_notify_service_plugin/files/schema.yml
teflo_notify_service_plugin/files/schema_extensions.py
teflo_notify_service_plugin-2.0.1.dist-info/AUTHORS
teflo_notify_service_plugin-2.0.1.dist-info/LICENSE
teflo_notify_service_plugin-2.0.1.dist-info/METADATA
teflo_notify_service_plugin-2.0.1.dist-info/WHEEL
teflo_notify_service_plugin-2.0.1.dist-info/entry_points.txt
teflo_notify_service_plugin-2.0.1.dist-info/top_level.txt
teflo_notify_service_plugin-2.0.1.dist-info/RECORD
