Metadata-Version: 2.1
Name: teflo_notify_service_plugin
Version: 2.0.1
Summary: Teflo plugin for integration with D&O tools's Notify Service 
Home-page: UNKNOWN
Author: Red Hat Inc
License: UNKNOWN
Platform: UNKNOWN
License-File: LICENSE
License-File: AUTHORS
